Pairs_Package2/__init__.py
Pairs_Package2/broker_info.py
Pairs_Package2/data.py
Pairs_Package2/setup.py
Pairs_Package2/signals.py
Pairs_Package2/trade.py
pairs_package2-0.1.7.dist-info/LICENSE
pairs_package2-0.1.7.dist-info/METADATA
pairs_package2-0.1.7.dist-info/WHEEL
pairs_package2-0.1.7.dist-info/top_level.txt
pairs_package2-0.1.7.dist-info/RECORD
