Metadata-Version: 2.2
Name: Pairs_Package2
Version: 0.1.7
Summary: Pairs Trading strategy, trades executed with Alpaca
Author: Mihai Posea
Author-email: pose4408@mylaurier.ca
Classifier: Programming Language :: Python :: 3.8
License-File: LICENSE
Requires-Dist: pandas
Requires-Dist: pandas_datareader
Requires-Dist: alpaca-trade-api
Requires-Dist: numpy
Requires-Dist: python-dotenv
Requires-Dist: setuptools
Requires-Dist: statsmodels
Dynamic: author
Dynamic: author-email
Dynamic: classifier
Dynamic: requires-dist
Dynamic: summary
